blurgenerator/__init__.py
blurgenerator/cli.py
blurgenerator/depth.py
blurgenerator/gaussian_blur.py
blurgenerator/lens_blur.py
blurgenerator/motion_blur.py
BlurGenerator-1.1.0.dist-info/LICENSE
BlurGenerator-1.1.0.dist-info/METADATA
BlurGenerator-1.1.0.dist-info/WHEEL
BlurGenerator-1.1.0.dist-info/entry_points.txt
BlurGenerator-1.1.0.dist-info/top_level.txt
BlurGenerator-1.1.0.dist-info/RECORD
