Metadata-Version: 2.1
Name: BlurGenerator
Version: 1.1.0
Summary: Fast generate blur image.
Home-page: https://github.com/NatLee/Blur-Generator
Author: Nat Lee
Author-email: natlee.work@gmail.com
Project-URL: Documentation, https://github.com/NatLee/Blur-Generator
Project-URL: Bug Reports, https://github.com/NatLee/Blur-Generator/issues
Project-URL: Source Code, https://github.com/NatLee/Blur-Generator
Keywords: blur,generator,blur-image,cli
Classifier: Development Status :: 5 - Production/Stable
Classifier: Intended Audience :: Developers
Classifier: Topic :: Software Development :: Build Tools
Classifier: Programming Language :: Python :: 3
Classifier: Programming Language :: Python :: 3.7
Classifier: Programming Language :: Python :: 3.8
Classifier: Programming Language :: Python :: 3.9
Classifier: Programming Language :: Python :: 3.10
Classifier: Programming Language :: Python :: 3.11
Classifier: Programming Language :: Python :: 3 :: Only
Classifier: License :: OSI Approved :: MIT License
Classifier: Operating System :: OS Independent
Requires-Python: >=3.7
License-File: LICENSE
Requires-Dist: opencv-python
Provides-Extra: dev
Requires-Dist: check-manifest ; extra == 'dev'
